hangman/__init__.py
hangman/__main__.py
hangman/_compat.py
hangman/controller.py
hangman/model.py
hangman/utils.py
hangman/view.py
python_hangman-2.2.3.dist-info/DESCRIPTION.rst
python_hangman-2.2.3.dist-info/METADATA
python_hangman-2.2.3.dist-info/RECORD
python_hangman-2.2.3.dist-info/WHEEL
python_hangman-2.2.3.dist-info/entry_points.txt
python_hangman-2.2.3.dist-info/metadata.json
python_hangman-2.2.3.dist-info/top_level.txt
