Metadata-Version: 1.1
Name: python_hangman
Version: 2.2.3
Summary: Python Hangman TDD/MVC demonstration.
Home-page: https://github.com/bionikspoon/python_hangman
Author: Manu Phatak
Author-email: bionikspoon@gmail.com
License: MIT
Keywords: python_hangman Manu Phatak
Platform: UNKNOWN
Classifier: Development Status :: 5 - Production/Stable
Classifier: Environment :: Console
Classifier: Intended Audience :: End Users/Desktop
Classifier: License :: OSI Approved :: MIT License
Classifier: Natural Language :: English
Classifier: Operating System :: OS Independent
Classifier: Programming Language :: Python
Classifier: Programming Language :: Python :: 2
Classifier: Programming Language :: Python :: 2.6
Classifier: Programming Language :: Python :: 2.7
Classifier: Programming Language :: Python :: 3
Classifier: Programming Language :: Python :: 3.3
Classifier: Programming Language :: Python :: 3.4
Classifier: Programming Language :: Python :: 3.5
Classifier: Programming Language :: Python :: Implementation :: CPython
Classifier: Programming Language :: Python :: Implementation :: PyPy
Classifier: Topic :: Games/Entertainment :: Puzzle Games
Classifier: Topic :: Terminals
